infinityfree/__init__.py
infinityfree/main.py
infinityfree-0.1.0.dist-info/METADATA
infinityfree-0.1.0.dist-info/WHEEL
infinityfree-0.1.0.dist-info/top_level.txt
infinityfree-0.1.0.dist-info/RECORD
